LICENSE
README.md
setup.cfg
setup.py
src/JestingLang/LexerParser.py
src/JestingLang/LexerParser_cachedParseTable.py
src/JestingLang/__init__.py
src/JestingLang/main.py
src/JestingLang/main_script.py
src/JestingLang.egg-info/PKG-INFO
src/JestingLang.egg-info/SOURCES.txt
src/JestingLang.egg-info/dependency_links.txt
src/JestingLang.egg-info/requires.txt
src/JestingLang.egg-info/top_level.txt
src/JestingLang/Core/__init__.py
src/JestingLang/Core/JDereferencer/AbstractDereferencer.py
src/JestingLang/Core/JDereferencer/CachedCellDereferencer.py
src/JestingLang/Core/JDereferencer/CachedDereferencer.py
src/JestingLang/Core/JDereferencer/KeyValueDereferencer.py
src/JestingLang/Core/JDereferencer/__init__.py
src/JestingLang/Core/JParsing/JestingAST.py
src/JestingLang/Core/JParsing/__init__.py
src/JestingLang/Core/JVisitors/AbstractJestingVisitor.py
src/JestingLang/Core/JVisitors/ContextBoundInterpreterVisitor.py
src/JestingLang/Core/JVisitors/ContextfreeInterpreterVisitor.py
src/JestingLang/Core/JVisitors/PrettyPrintingVisitors.py
src/JestingLang/Core/JVisitors/ReferencesListerVisitor.py
src/JestingLang/Core/JVisitors/__init__.py
src/JestingLang/JestingScript/__init__.py
src/JestingLang/JestingScript/JDereferencer/ScriptDereferencer.py
src/JestingLang/JestingScript/JDereferencer/__init__.py
src/JestingLang/JestingScript/JParsing/JestingScriptAST.py
src/JestingLang/JestingScript/JParsing/__init__.py
src/JestingLang/JestingScript/JVisitors/ScriptInterpreterVisitor.py
src/JestingLang/JestingScript/JVisitors/__init__.py
src/JestingLang/Misc/__init__.py
src/JestingLang/Misc/JLogic/LogicFunctions.py
src/JestingLang/Misc/JLogic/OperationMapping.py
src/JestingLang/Misc/JLogic/__init__.py
src/JestingLang/Misc/JTesting/DereferencerHelper.py
src/JestingLang/Misc/JTesting/LexerParserHelpers.py
src/JestingLang/Misc/JTesting/NonFileExternalFileLoader.py
src/JestingLang/Misc/JTesting/__init__.py