Metadata-Version: 2.1
Name: JestingLang
Version: 0.0.0a10
Summary: A compiler for the minimalist spreadsheet language Jesting
Home-page: https://github.com/itruffat/JestingLang
Author: itrufat
License: UNKNOWN
Platform: UNKNOWN
Classifier: Development Status :: 3 - Alpha
Classifier: Intended Audience :: Developers
Classifier: License :: OSI Approved :: MIT License
Classifier: Programming Language :: Python :: 3
Classifier: Programming Language :: Python :: 3.6
Classifier: Programming Language :: Python :: 3.7
Classifier: Programming Language :: Python :: 3.8
Classifier: Programming Language :: Python :: 3.9
License-File: LICENSE
